{
  "verb": "achunchar",
  "definition": null,
  "reflexive": false,
  "spanishdict": {
    "Indicative": {
      "Present": [
        "me achuncho",
        "te achunchas",
        "se achuncha",
        "nos achunchamos",
        "os achuncháis",
        "se achunchan"
      ],
      "Preterite": [
        "me achunché",
        "te achunchaste",
        "se achunchó",
        "nos achunchamos",
        "os achunchasteis",
        "se achuncharon"
      ],
      "Imperfect": [
        "me achunchaba",
        "te achunchabas",
        "se achunchaba",
        "nos achunchábamos",
        "os achunchabais",
        "se achunchaban"
      ],
      "Conditional": [
        "me achuncharía",
        "te achuncharías",
        "se achuncharía",
        "nos achuncharíamos",
        "os achuncharíais",
        "se achuncharían"
      ],
      "Future": [
        "me achuncharé",
        "te achuncharás",
        "se achunchará",
        "nos achuncharemos",
        "os achuncharéis",
        "se achuncharán"
      ]
    },
    "Subjunctive": {
      "Present": [
        "me achunche",
        "te achunches",
        "se achunche",
        "nos achunchemos",
        "os achunchéis",
        "se achunchen"
      ],
      "Imperfect (-ra)": [
        "me achunchara",
        "te achuncharas",
        "se achunchara",
        "nos achuncháramos",
        "os achuncharais",
        "se achuncharan"
      ],
      "Imperfect (-se)": [
        "me achunchase",
        "te achunchases",
        "se achunchase",
        "nos achunchásemos",
        "os achunchaseis",
        "se achunchasen"
      ],
      "Future": [
        "me achunchare",
        "te achunchares",
        "se achunchare",
        "nos achuncháremos",
        "os achunchareis",
        "se achuncharen"
      ]
    },
    "Imperative": {
      "Affirmative": ["achúnchate", "achúnchese", "achunchémonos", "achunchaos", "achúnchense"],
      "Negative": [
        "no te achunches",
        "no se achunche",
        "no nos achunchemos",
        "no os achunchéis",
        "no se achunchen"
      ]
    },
    "Present Participle": "achunchando",
    "Past Participle": "achunchado"
  },
  "spanishdictLink": "http://www.spanishdict.com/conjugate/achuncharse",
  "wordreference": {
    "Indicative": {
      "Present": [
        "me achuncho",
        "te achunchas",
        "se achuncha",
        "nos achunchamos",
        "os achuncháis",
        "se achunchan"
      ],
      "Preterite": [
        "me achunché",
        "te achunchaste",
        "se achunchó",
        "nos achunchamos",
        "os achunchasteis",
        "se achuncharon"
      ],
      "Imperfect": [
        "me achunchaba",
        "te achunchabas",
        "se achunchaba",
        "nos achunchábamos",
        "os achunchabais",
        "se achunchaban"
      ],
      "Conditional": [
        "me achuncharía",
        "te achuncharías",
        "se achuncharía",
        "nos achuncharíamos",
        "os achuncharíais",
        "se achuncharían"
      ],
      "Future": [
        "me achuncharé",
        "te achuncharás",
        "se achunchará",
        "nos achuncharemos",
        "os achuncharéis",
        "se achuncharán"
      ]
    },
    "Subjunctive": {
      "Present": [
        "me achunche",
        "te achunches",
        "se achunche",
        "nos achunchemos",
        "os achunchéis",
        "se achunchen"
      ],
      "Imperfect (-ra)": [
        "me achunchara",
        "te achuncharas",
        "se achunchara",
        "nos achuncháramos",
        "os achuncharais u os achunchaseis",
        "se achuncharan"
      ],
      "Imperfect (-se)": [
        "me achunchase",
        "te achunchases",
        "se achunchase",
        "nos achunchásemos",
        "os achunchaseis",
        "se achunchasen"
      ],
      "Future": [
        "me achunchare",
        "te achunchares",
        "se achunchare",
        "nos achuncháremos",
        "os achunchareis",
        "se achuncharen"
      ]
    },
    "Imperative": {
      "Affirmative": ["achúnchate", "achúnchese", "achunchémonos", "achunchaos", "achúnchense"],
      "Negative": [
        "no te achunches",
        "no se achunche",
        "no nos achunchemos",
        "no os achunchéis",
        "no se achunchen"
      ]
    },
    "Present Participle": "achunchando",
    "Past Participle": "achunchado"
  },
  "wordreferenceLink": "http://www.wordreference.com/es/en/translation.asp?spen=achuncharse"
}
