{
  "verb": "aflautar",
  "definition": null,
  "reflexive": false,
  "spanishdict": null,
  "spanishdictLink": "http://www.spanishdict.com/conjugate/aflautar",
  "wordreference": {
    "Indicative": {
      "Present": ["aflauto", "aflautas", "aflauta", "aflautamos", "aflautáis", "aflautan"],
      "Preterite": ["aflauté", "aflautaste", "aflautó", "aflautamos", "aflautasteis", "aflautaron"],
      "Imperfect": [
        "aflautaba",
        "aflautabas",
        "aflautaba",
        "aflautábamos",
        "aflautabais",
        "aflautaban"
      ],
      "Conditional": [
        "aflautaría",
        "aflautarías",
        "aflautaría",
        "aflautaríamos",
        "aflautaríais",
        "aflautarían"
      ],
      "Future": [
        "aflautaré",
        "aflautarás",
        "aflautará",
        "aflautaremos",
        "aflautaréis",
        "aflautarán"
      ]
    },
    "Subjunctive": {
      "Present": ["aflaute", "aflautes", "aflaute", "aflautemos", "aflautéis", "aflauten"],
      "Imperfect (-ra)": [
        "aflautara",
        "aflautaras",
        "aflautara",
        "aflautáramos",
        "aflautarais",
        "aflautaran"
      ],
      "Imperfect (-se)": [
        "aflautase",
        "aflautases",
        "aflautase",
        "aflautásemos",
        "aflautaseis",
        "aflautasen"
      ],
      "Future": [
        "aflautare",
        "aflautares",
        "aflautare",
        "aflautáremos",
        "aflautareis",
        "aflautaren"
      ]
    },
    "Imperative": {
      "Affirmative": ["aflauta", "aflaute", "aflautemos", "aflautad", "aflauten"],
      "Negative": ["no aflautes", "no aflaute", "no aflautemos", "no aflautéis", "no aflauten"]
    },
    "Present Participle": "aflautando",
    "Past Participle": "aflautado"
  },
  "wordreferenceLink": "http://www.wordreference.com/es/en/translation.asp?spen=aflautar"
}
